{"cameraMode":{"drawMode":0,"name":"Shaded","section":"Shading Mode"},"sceneLighting":false,"audioPlay":false,"sceneViewState":{"showFog":true,"showMaterialUpdate":false,"showSkybox":false,"showFlares":true,"showImageEffects":true,"showParticleSystems":true},"in2DMode":false,"pivot":{"x":-0.02500009536743164,"y":5.556124210357666,"z":108.02272033691406},"rotation":{"x":-0.14333386719226838,"y":0.3152659237384796,"z":-0.048227641731500629,"w":-0.9368911385536194},"size":3.2482733726501467,"orthographic":false}